main.py
utils.py
dvtagcc/__init__.py
dvtagcc/doujinvoice.py
dvtagcc/dvtagcc.py
dvtagcc/utils.py
dvtagcc-0.6.41.dist-info/LICENSE
dvtagcc-0.6.41.dist-info/METADATA
dvtagcc-0.6.41.dist-info/WHEEL
dvtagcc-0.6.41.dist-info/entry_points.txt
dvtagcc-0.6.41.dist-info/top_level.txt
dvtagcc-0.6.41.dist-info/RECORD
