Metadata-Version: 2.1
Name: dvtagcc
Version: 0.6.41
Summary: A tool for tagging your doujin voice library.
Home-page: https://github.com/GodCC6/dvtagcc
Author: CC
Author-email: zhoucc922@gmail.com
Classifier: Programming Language :: Python :: 3
Classifier: License :: OSI Approved :: MIT License
Classifier: Operating System :: OS Independent
Requires-Python: >=3.9
License-File: LICENSE
Requires-Dist: certifi
Requires-Dist: charset-normalizer
Requires-Dist: idna
Requires-Dist: mutagen
Requires-Dist: natsort
Requires-Dist: Pillow
Requires-Dist: requests
Requires-Dist: urllib3
